gsc/__init__.py
gsc/auth.py
gsc/cli.py
gsc/client.py
gsc/exercises/__init__.py
gsc/exercises/amend.py
gsc/exercises/merge_conflict.py
gsc/exercises/multiple_remotes.py
gsc/exercises/my_first_commit.py
gsc/exercises/push_and_pull.py
gsc/exercises/reset_file.py
gsc/exercises/revert.py
gsc/exercises/ssh_clone.py
gsc/exercises/sync_error.py
gsc/exercises/use_the_force.py
gsc/exercises/utils.py
gsc/reset_exercise.py
gsc/setup_exercise.py
gsc/verifier.py
gsc-3.0.0.dist-info/WHEEL
gsc-3.0.0.dist-info/LICENSE
gsc-3.0.0.dist-info/entry_points.txt
gsc-3.0.0.dist-info/METADATA
gsc-3.0.0.dist-info/RECORD
