Metadata-Version: 2.1
Name: gsc
Version: 3.0.0
Summary: Git for Scientists practical exercise helper.
Home-page: https://www.gitscientist.com
License: GPL-3.0-only
Author: Daniel Tipping
Author-email: daniel@gitscientist.com
Requires-Python: >=3.9,<4.0
Classifier: License :: OSI Approved :: GNU General Public License v3 (GPLv3)
Classifier: Programming Language :: Python :: 3
Classifier: Programming Language :: Python :: 3.9
Classifier: Programming Language :: Python :: 3.10
Classifier: Programming Language :: Python :: 3.11
Requires-Dist: asyncio (>=3.4.3,<4.0.0)
Requires-Dist: requests (>=2.24.0,<3.0.0)
Requires-Dist: typer (>=0.1.1,<0.2.0)
Requires-Dist: websockets (>=10,<11)
Project-URL: Repository, https://github.com/git-scientist/gsc
